ahapy/__init__.py
ahapy-0.0.7.dist-info/LICENSE.md
ahapy-0.0.7.dist-info/METADATA
ahapy-0.0.7.dist-info/WHEEL
ahapy-0.0.7.dist-info/top_level.txt
ahapy-0.0.7.dist-info/RECORD
