Metadata-Version: 2.1
Name: ahapy
Version: 0.0.7
Summary: A small Aha.io API client
Home-page: https://github.com/henkhaus/ahapy
Author: Robert Henkhaus
Author-email: rhenkhaus@gmail.com
License: UNKNOWN
Project-URL: Bug Tracker, https://github.com/henkhaus/ahapy/issues
Keywords: aha,aha.io
Platform: UNKNOWN
Classifier: Programming Language :: Python :: 3
Classifier: License :: OSI Approved :: MIT License
Classifier: Operating System :: OS Independent
Requires-Python: >=3.6
Requires-Dist: requests (>=2.22.0)
